matsh/__init__.py
matsh/core.py
matsh-0.1.0.dist-info/licenses/LICENSE
matsh-0.1.0.dist-info/METADATA
matsh-0.1.0.dist-info/WHEEL
matsh-0.1.0.dist-info/top_level.txt
matsh-0.1.0.dist-info/RECORD
